{
    "c": {
        "a": [["s", 0.35, "hp100"], ["sp", 0.05]],
        "att": 476,
        "ele": "shadow",
        "stars": "4",
        "wt": "dagger",
        "name": "Alex",
        "spiral": 0
    },
    "s1": {
        "buff": ["debuff", 0.05, 10.0, 0.4],
        "dmg": 6.64,
        "hit": 4,
        "recovery": 2.3,
        "sp": 2243,
        "startup": 0.1
    },
    "s2": {
        "dmg": 6.05,
        "hit": 5,
        "recovery": 2.05,
        "sp": 4925,
        "startup": 0.1
    }
}