{
    "c": {
        "name": "Durant",
        "icon": "110343_01_r04",
        "att": 505,
        "hp": 716,
        "ele": "shadow",
        "wt": "blade",
        "spiral": false,
        "a": [["a", 0.13, "hp100"], ["cd", 0.17, "hp100"]]
    },
    "s1": {
        "sp": 2987,
        "startup": 0.1,
        "recovery": 1.0,
        "attr": [
            {"buff": [["self", 0.35, 20.0, "att", "buff"], ["team", 0.05, 20.0, "att", "buff"]], "iv": 0.13333}
        ]
    },
    "s2": {
        "sp": 4139,
        "startup": 0.1,
        "recovery": 1.0,
        "attr": [
            {"buff": ["self", 0.3, 20.0, "crit", "chance"], "iv": 0.13333}
        ]
    }
}