{
  "180": {
    "base": {
      "dps": 45165.353639545094,
      "team": 0.0,
      "tdps": null,
      "slots.a": [
        "Howling_to_the_Heavens",
        "Memory_of_a_Friend",
        "The_Shining_Overlord",
        "Beautiful_Nothingness",
        "The_Plaguebringer"
      ],
      "slots.d": "Gala_Cat_Sith",
      "acl": [
        "`dragon(c3-s-end), self.trickery <= 1",
        "`s3, not buff(s3) and fsc",
        "`s2",
        "`s4, cancel",
        "`s1, cancel",
        "`fs, x=4"
      ],
      "coabs": [
        "Blade",
        "Wand",
        "Gala_Alex"
      ],
      "share": [
        "Weapon",
        "Rodrigo"
      ]
    },
    "pref": "base",
    "affliction": {
      "dps": 59159.058743321024,
      "team": 0.0,
      "tdps": null,
      "slots.a": [
        "Howling_to_the_Heavens",
        "Memory_of_a_Friend",
        "The_Shining_Overlord",
        "His_Clever_Brother",
        "The_Plaguebringer"
      ],
      "slots.d": "Gala_Cat_Sith",
      "acl": [
        "`dragon(c3-s-end), self.trickery <= 1",
        "`s3, not buff(s3) and fsc",
        "`s2",
        "`s4, cancel",
        "`s1, cancel",
        "`fs, x=4"
      ],
      "coabs": [
        "Blade",
        "Wand",
        "Bow"
      ],
      "share": [
        "Weapon",
        "Fjorm"
      ]
    }
  }
}