{
  "SELF-NORMAL-ANY": {
    "TEAMBUFF": {
      "EQMT": {
        "dps": 7359.685596724616,
        "team": 1.1925898221012248,
        "noaff": true,
        "nihil": false
      },
      "slots.a": [
        "Jewels_of_the_Sun",
        "Sisters_Day_Out",
        "Wily_Warriors_Flash_and_Heat",
        "Bellathorna",
        "From_Whence_He_Comes"
      ],
      "slots.d": "Azazel",
      "acl": [
        "`s3, not buff(s3) and prep",
        "`s2",
        "`s4",
        "`fs, x=5"
      ],
      "coabs": [
        "Bow",
        "Joker",
        "Tobias"
      ],
      "share": [
        "Weapon",
        "Karl"
      ]
    },
    "PERSONAL": {
      "EQMT": {
        "dps": 61815.08587146766,
        "team": 0.20787035345848234,
        "noaff": false,
        "nihil": false
      },
      "slots.a": [
        "Dragon_and_Tamer",
        "Memory_of_a_Friend",
        "Sweet_Surprise",
        "The_Plaguebringer",
        "The_Queen_of_the_Knife"
      ],
      "slots.d": "Gala_Cat_Sith",
      "acl": [
        "`dragon(c3-s-end), cancel",
        "`s3, not buff(s3) and prep",
        "`s2",
        "`s4, cancel",
        "`s1, bleed_stack<3",
        "`fs, x=5"
      ],
      "coabs": [
        "Delphi",
        "Ieyasu",
        "Vania"
      ],
      "share": [
        "Weapon",
        "Formal_Joachim"
      ]
    },
    "META": {
      "tdps": 55300.42007781156,
      "pref": "PERSONAL"
    }
  },
  "SELF-NORMAL-MONO": {
    "TEAMBUFF": {
      "EQMT": {
        "dps": 6976.165943072496,
        "team": 0.9054150785584295,
        "noaff": true,
        "nihil": false
      },
      "coabs": [
        "Delphi",
        "Ieyasu",
        "Wand"
      ]
    },
    "META": {
      "tdps": 78617.06634013698,
      "pref": "PERSONAL",
      "partial": {
        "PERSONAL": "SELF-NORMAL-ANY",
        "TEAMBUFF": "SELF-NORMAL-ANY"
      }
    }
  },
  "SELF-NIHILISM-ANY": {
    "TEAMBUFF": {
      "EQMT": {
        "dps": 33387.28300691452,
        "team": 0.020465240582629416,
        "noaff": false,
        "nihil": true
      },
      "slots.a": [
        "Dragon_and_Tamer",
        "Howling_to_the_Heavens",
        "Memory_of_a_Friend",
        "The_Plaguebringer",
        "The_Queen_of_the_Knife"
      ],
      "slots.d": "Arsene",
      "acl": [
        "`dragon",
        "`s3",
        "`s4, cancel",
        "`s1, bleed_stack<3",
        "`fs, x=5"
      ],
      "coabs": [
        "Delphi",
        "Ieyasu",
        "Wand"
      ],
      "share": [
        "Ranzal",
        "Curran"
      ]
    },
    "PERSONAL": {
      "EQMT": {
        "dps": 39120.13092386516,
        "team": 0.0,
        "noaff": false,
        "nihil": true
      },
      "slots.a": [
        "Dragon_and_Tamer",
        "Memory_of_a_Friend",
        "Welcome_to_the_Opera",
        "The_Plaguebringer",
        "The_Queen_of_the_Knife"
      ],
      "slots.d": "Arsene",
      "acl": [
        "`dragon(c3-s-end)",
        "`s1, bleed_stack<3",
        "`s4",
        "`s3",
        "`fs, x=5"
      ],
      "coabs": [
        "Ieyasu",
        "Joker",
        "Wand"
      ],
      "share": [
        "Gala_Chelle",
        "Ranzal"
      ]
    },
    "META": {
      "tdps": 280126.0944773155,
      "pref": "PERSONAL"
    }
  },
  "ALWAYS-NORMAL-ANY": {
    "PERSONAL": {
      "EQMT": {
        "dps": 62582.335310446026,
        "team": 0.18686249847992892,
        "noaff": false,
        "nihil": false
      },
      "slots.a": [
        "A_Man_Unchanging",
        "Dragon_and_Tamer",
        "Memory_of_a_Friend",
        "His_Clever_Brother",
        "The_Queen_of_the_Knife"
      ],
      "acl": [
        "`dragon(c3-s-end), trickery<=1",
        "`s3, not buff(s3) and prep",
        "`s2, cancel",
        "`s4, cancel",
        "`s1",
        "`fs, x=5"
      ],
      "coabs": [
        "Dagger",
        "Ieyasu",
        "Wand"
      ],
      "share": [
        "Weapon",
        "Fjorm"
      ]
    },
    "META": {
      "tdps": 54908.17283842173,
      "pref": "PERSONAL",
      "partial": {
        "PERSONAL": "SELF-NORMAL-ANY",
        "TEAMBUFF": "SELF-NORMAL-ANY"
      }
    }
  },
  "ALWAYS-NIHILISM-ANY": {
    "TEAMBUFF": {
      "EQMT": {
        "dps": 38262.17133877222,
        "team": 0.020465240582629416,
        "noaff": false,
        "nihil": true
      }
    },
    "PERSONAL": {
      "EQMT": {
        "dps": 44663.988407476805,
        "team": 0.0,
        "noaff": false,
        "nihil": true
      },
      "acl": [
        "`dragon(c5-s-c3-end)",
        "`s1, bleed_stack<3",
        "`s4",
        "`s3",
        "`fs, x=5"
      ],
      "share": [
        "Gala_Chelle",
        "Summer_Julietta"
      ]
    },
    "META": {
      "tdps": 312814.16130227904,
      "pref": "PERSONAL",
      "partial": {
        "PERSONAL": "SELF-NIHILISM-ANY",
        "TEAMBUFF": "SELF-NIHILISM-ANY"
      }
    }
  },
  "IMMUNE-NORMAL-ANY": {
    "PERSONAL": {
      "EQMT": {
        "dps": 40505.930684613755,
        "team": 0.2273694441571031,
        "noaff": false,
        "nihil": false
      },
      "slots.a": [
        "Dragon_and_Tamer",
        "Jewels_of_the_Sun",
        "Memory_of_a_Friend",
        "Snipers_Allure",
        "The_Queen_of_the_Knife"
      ]
    },
    "META": {
      "tdps": 34340.59811137559,
      "pref": "TEAMBUFF",
      "partial": {
        "PERSONAL": "SELF-NORMAL-ANY",
        "TEAMBUFF": "SELF-NORMAL-ANY"
      }
    }
  },
  "IMMUNE-NIHILISM-ANY": {
    "TEAMBUFF": {
      "EQMT": {
        "dps": 28427.526417931007,
        "team": 0.020465240582629416,
        "noaff": false,
        "nihil": true
      }
    },
    "PERSONAL": {
      "EQMT": {
        "dps": 30442.401789360418,
        "team": 0.0,
        "noaff": false,
        "nihil": true
      },
      "acl": [
        "`dragon(c5-s-c3-end)",
        "`s1, bleed_stack<3",
        "`s4",
        "`s3",
        "`fs, x=5"
      ],
      "share": [
        "Gala_Chelle",
        "Summer_Julietta"
      ]
    },
    "META": {
      "tdps": 98453.53946826338,
      "pref": "PERSONAL",
      "partial": {
        "PERSONAL": "SELF-NIHILISM-ANY",
        "TEAMBUFF": "SELF-NIHILISM-ANY"
      }
    }
  }
}