{
  "180": {
    "pref": "base",
    "mono_pref": "mono_base",
    "base": {
      "dps": 73110.41770085208,
      "team": 0.0,
      "tdps": null,
      "slots.a": [
        "Memory_of_a_Friend",
        "The_Lurker_in_the_Woods",
        "Welcome_to_the_Opera",
        "Enter_the_Blue_Rose",
        "Luck_of_the_Draw"
      ],
      "slots.d": "High_Chthonius",
      "acl": [
        "`dragon(c3-s-end), s",
        "`s3, not buff(s3)",
        "`s1, not aff(shadowblight)",
        "`s4",
        "`fs"
      ],
      "coabs": [
        "Forte",
        "Grace",
        "Ieyasu"
      ],
      "share": [
        "Weapon",
        "Summer_Luca"
      ]
    },
    "affliction": {
      "dps": 83728.88454571192,
      "team": 0.0,
      "tdps": null,
      "slots.a": [
        "Memory_of_a_Friend",
        "The_Lurker_in_the_Woods",
        "Welcome_to_the_Opera",
        "Enter_the_Blue_Rose",
        "The_Plaguebringer"
      ],
      "slots.d": "High_Chthonius",
      "acl": [
        "`dragon(c3-s-end), s",
        "`s3, not buff(s3)",
        "`s1, not aff(shadowblight)",
        "`s4",
        "`fs"
      ],
      "coabs": [
        "Forte",
        "Grace",
        "Ieyasu"
      ],
      "share": [
        "Weapon",
        "Summer_Luca"
      ]
    },
    "buffer": {
      "dps": 11530.797348398719,
      "team": 0.45259298339182374,
      "tdps": 136059.60015323962,
      "slots.a": [
        "Castle_Cheer_Corps",
        "Dazzling_Duet",
        "Jewels_of_the_Sun",
        "Luck_of_the_Draw",
        "Seaside_Memory"
      ],
      "slots.d": "Azazel",
      "acl": [
        "`s3",
        "`s4",
        "`fs"
      ],
      "coabs": [
        "Blade",
        "Bow",
        "Joker"
      ],
      "share": [
        "Patia",
        "Templar_Hope"
      ]
    },
    "noaffliction": {
      "dps": 63021.90512608255,
      "team": 0.0,
      "tdps": null,
      "slots.a": [
        "Memory_of_a_Friend",
        "Moonlight_Party",
        "The_Lurker_in_the_Woods",
        "Enter_the_Blue_Rose",
        "Luck_of_the_Draw"
      ],
      "slots.d": "High_Chthonius",
      "acl": [
        "`dragon(s-end)",
        "`s3, not buff(s3)",
        "`s4",
        "`fs"
      ],
      "coabs": [
        "Blade",
        "Dagger",
        "Grace"
      ],
      "share": [
        "Weapon",
        "Summer_Luca"
      ]
    }
  }
}