{
  "SELF-NORMAL-ANY": {
    "TEAMBUFF": {
      "EQMT": {
        "dps": 6032.467023425319,
        "team": 0.5556812942363325,
        "noaff": true,
        "nihil": false
      },
      "slots.a": [
        "Jewels_of_the_Sun",
        "Study_Rabbits",
        "Warrior_Maiden",
        "Bellathorna",
        "From_Whence_He_Comes"
      ],
      "slots.d": "PopStar_Siren",
      "slots.w": "chimeratech",
      "acl": [
        "`dragon",
        "`s3",
        "`s4",
        "`s1, not buff(s1)"
      ],
      "coabs": [
        "Bow",
        "The_Prince",
        "Tobias"
      ],
      "share": [
        "Chitose",
        "Yuya"
      ]
    },
    "PERSONAL": {
      "EQMT": {
        "dps": 55632.783759806196,
        "team": 0.09676588863729087,
        "noaff": true,
        "nihil": false
      },
      "slots.a": [
        "An_Ancient_Oath",
        "Emissaries_of_the_Heavens",
        "The_Bridal_Dragon",
        "Dueling_Dancers",
        "Such_High_Spirits",
        "An_Unfreezing_Flower_Deer",
        "Testament_of_Eternity"
      ],
      "slots.d": "Daikokuten",
      "acl": [
        "`s1, dgauge>=500 and not buff(s1)",
        "`dragon, xf and buff(s3,1)",
        "`s4, xf>2",
        "`s3, xf>3"
      ],
      "dacl": [
        "ds1,x=3"
      ],
      "coabs": [
        "Dagger2",
        "Peony",
        "Raemond"
      ],
      "share": [
        "Weapon",
        "Gala_Mym"
      ]
    },
    "META": {
      "tdps": 108081.61184224245,
      "pref": "PERSONAL"
    }
  },
  "SELF-NORMAL-MONO": {
    "PERSONAL": {
      "EQMT": {
        "dps": 52941.38246099769,
        "team": 0.09676588863729087,
        "noaff": true,
        "nihil": false
      },
      "coabs": [
        "Blade",
        "Peony",
        "Raemond"
      ]
    },
    "META": {
      "tdps": 971051.4221954164,
      "pref": "PERSONAL",
      "partial": {
        "PERSONAL": "SELF-NORMAL-ANY"
      }
    }
  },
  "SELF-NIHILISM-ANY": {
    "TEAMBUFF": {
      "EQMT": {
        "dps": 5052.5437012699895,
        "team": 0.16555630309643235,
        "noaff": true,
        "nihil": true
      },
      "slots.a": [
        "Castle_Cheer_Corps",
        "Jewels_of_the_Sun",
        "Study_Rabbits",
        "Blessed_Days",
        "Seaside_Memory",
        "Mask_of_Determination_Bow",
        "Testament_of_Eternity"
      ],
      "slots.d": "Tie_Shan_Gongzhu",
      "acl": [
        "`s2",
        "`s3",
        "`s4"
      ],
      "coabs": [
        "Bow",
        "Peony",
        "Sha_Wujing"
      ],
      "share": [
        "Rawn",
        "Sha_Wujing"
      ]
    },
    "PERSONAL": {
      "EQMT": {
        "dps": 30451.326196215825,
        "team": 0.0,
        "noaff": false,
        "nihil": true
      },
      "slots.a": [
        "An_Ancient_Oath",
        "Emissaries_of_the_Heavens",
        "The_Bridal_Dragon",
        "Dueling_Dancers",
        "Such_High_Spirits",
        "An_Unfreezing_Flower_Deer",
        "Testament_of_Eternity"
      ],
      "slots.d": "High_Jupiter",
      "acl": [
        "`dragon",
        "`s4",
        "`s3"
      ],
      "coabs": [
        "Blade",
        "Dagger",
        "Peony"
      ],
      "share": [
        "Weapon",
        "Gala_Mym"
      ]
    },
    "META": {
      "tdps": 153414.77201355292,
      "pref": "PERSONAL"
    }
  },
  "ALWAYS-NIHILISM-ANY": {
    "PERSONAL": {
      "EQMT": {
        "dps": 38644.14974332128,
        "team": 0.0,
        "noaff": false,
        "nihil": true
      },
      "slots.a": [
        "Extreme_Teamwork",
        "Pecorines_Grand_Adventure",
        "Spirit_of_the_Season",
        "A_Small_Courage",
        "Dueling_Dancers",
        "Mask_of_Determination_Bow",
        "Testament_of_Eternity"
      ],
      "acl": [
        "`dragon, aff(flashburn)",
        "`s4, x=5",
        "`s3"
      ],
      "share": [
        "Summer_Julietta",
        "Summer_Celliera"
      ]
    },
    "META": {
      "tdps": 202901.40220445144,
      "pref": "PERSONAL",
      "partial": {
        "PERSONAL": "SELF-NIHILISM-ANY",
        "TEAMBUFF": "SELF-NIHILISM-ANY"
      }
    }
  },
  "IMMUNE-NIHILISM-ANY": {
    "PERSONAL": {
      "EQMT": {
        "dps": 20722.315453015948,
        "team": 0.0,
        "noaff": true,
        "nihil": true
      },
      "slots.d": "Jeanne_dArc"
    },
    "META": {
      "tdps": 94649.20065664135,
      "pref": "PERSONAL",
      "partial": {
        "PERSONAL": "SELF-NIHILISM-ANY",
        "TEAMBUFF": "SELF-NIHILISM-ANY"
      }
    }
  }
}