{
  "SELF-NORMAL-ANY": {
    "TEAMBUFF": {
      "EQMT": {
        "dps": 41943.894895811616,
        "team": 0.06894295080164793,
        "noaff": false,
        "nihil": false
      },
      "slots.a": [
        "An_Ancient_Oath",
        "Extreme_Teamwork",
        "Memory_of_a_Friend",
        "A_Small_Courage",
        "Dueling_Dancers",
        "Mask_of_Determination_Bow",
        "Testament_of_Eternity"
      ],
      "slots.d": "Daikokuten",
      "acl": [
        "`dragon(s), buff(s3, 1)",
        "`s1",
        "`s2",
        "`s3",
        "`s4"
      ],
      "coabs": [
        "Blade",
        "Bow",
        "Peony"
      ],
      "share": [
        "Weapon",
        "Ilia"
      ]
    },
    "PERSONAL": {
      "EQMT": {
        "dps": 43211.967350343366,
        "team": 0.0657922449268746,
        "noaff": false,
        "nihil": false
      },
      "slots.a": [
        "An_Ancient_Oath",
        "Extreme_Teamwork",
        "Memory_of_a_Friend",
        "A_Small_Courage",
        "Dueling_Dancers",
        "Mask_of_Determination_Bow",
        "Testament_of_Eternity"
      ],
      "slots.d": "Daikokuten",
      "acl": [
        "`dragon(c3), buff(s3, 1)",
        "`s1",
        "`s2",
        "`s3",
        "`s4"
      ],
      "coabs": [
        "Blade",
        "Bow",
        "Peony"
      ],
      "share": [
        "Weapon",
        "Ilia"
      ]
    },
    "META": {
      "tdps": 402472.49503192026,
      "pref": "PERSONAL"
    }
  },
  "SELF-NIHILISM-ANY": {
    "PERSONAL": {
      "EQMT": {
        "dps": 19840.877467065467,
        "team": 0.04868282555338913,
        "noaff": false,
        "nihil": true
      },
      "slots.a": [
        "An_Ancient_Oath",
        "Extreme_Teamwork",
        "Memory_of_a_Friend",
        "A_Small_Courage",
        "Dueling_Dancers",
        "Mask_of_Determination_Bow",
        "Testament_of_Eternity"
      ],
      "slots.d": "Daikokuten",
      "acl": [
        "`dragon(s), buff(s3, 1)",
        "`s1",
        "`s2",
        "`s3",
        "`s4"
      ],
      "coabs": [
        "Blade",
        "Bow",
        "Peony"
      ],
      "share": [
        "Weapon",
        "Ilia"
      ]
    },
    "META": {
      "pref": "PERSONAL"
    }
  },
  "ALWAYS-NORMAL-ANY": {
    "TEAMBUFF": {
      "EQMT": {
        "dps": 47068.33960824694,
        "team": 0.06894295080164793,
        "noaff": false,
        "nihil": false
      }
    },
    "PERSONAL": {
      "EQMT": {
        "dps": 51002.990116255125,
        "team": 0.06579224492687456,
        "noaff": false,
        "nihil": false
      },
      "slots.a": [
        "Extreme_Teamwork",
        "Memory_of_a_Friend",
        "Spirit_of_the_Season",
        "A_Passion_for_Produce",
        "A_Small_Courage",
        "Mask_of_Determination_Bow",
        "Testament_of_Eternity"
      ],
      "coabs": [
        "Bow",
        "Dagger2",
        "Peony"
      ]
    },
    "META": {
      "tdps": 1248815.5557494573,
      "pref": "PERSONAL",
      "partial": {
        "PERSONAL": "SELF-NORMAL-ANY",
        "TEAMBUFF": "SELF-NORMAL-ANY"
      }
    }
  },
  "ALWAYS-NORMAL-MONO": {
    "PERSONAL": {
      "EQMT": {
        "dps": 47068.33960824694,
        "team": 0.06894295080164793,
        "noaff": false,
        "nihil": false
      },
      "acl": [
        "`dragon(s), buff(s3, 1)",
        "`s1",
        "`s2",
        "`s3",
        "`s4"
      ]
    },
    "META": {
      "pref": "PERSONAL",
      "partial": {
        "PERSONAL": "SELF-NORMAL-ANY",
        "TEAMBUFF": "ALWAYS-NORMAL-ANY"
      }
    }
  },
  "ALWAYS-NIHILISM-ANY": {
    "PERSONAL": {
      "EQMT": {
        "dps": 41393.05140383148,
        "team": 0.04022895748154666,
        "noaff": false,
        "nihil": true
      },
      "slots.a": [
        "Extreme_Teamwork",
        "Memory_of_a_Friend",
        "Spirit_of_the_Season",
        "A_Passion_for_Produce",
        "A_Small_Courage",
        "Mask_of_Determination_Bow",
        "Testament_of_Eternity"
      ],
      "slots.d": "Gala_Reborn_Jeanne",
      "acl": [
        "`dragon(c3-s-c3-c3-c3-end), aff(flashburn)",
        "`s4",
        "`s3",
        "`s1",
        "`s2, x=5"
      ],
      "coabs": [
        "Blade",
        "Peony",
        "Wand"
      ],
      "share": [
        "Gala_Mym",
        "Ilia"
      ]
    },
    "META": {
      "pref": "PERSONAL",
      "partial": {
        "PERSONAL": "SELF-NIHILISM-ANY",
        "TEAMBUFF": "SELF-NORMAL-ANY"
      }
    }
  },
  "IMMUNE-NORMAL-ANY": {
    "TEAMBUFF": {
      "EQMT": {
        "dps": 36777.608659005346,
        "team": 0.06894295080164771,
        "noaff": false,
        "nihil": false
      }
    },
    "PERSONAL": {
      "EQMT": {
        "dps": 38257.04854941303,
        "team": 0.0657922449268746,
        "noaff": false,
        "nihil": false
      }
    },
    "META": {
      "tdps": 469558.2352682249,
      "pref": "PERSONAL",
      "partial": {
        "PERSONAL": "SELF-NORMAL-ANY",
        "TEAMBUFF": "SELF-NORMAL-ANY"
      }
    }
  },
  "IMMUNE-NIHILISM-ANY": {
    "PERSONAL": {
      "EQMT": {
        "dps": 23942.315980449912,
        "team": 0.049947800258281876,
        "noaff": false,
        "nihil": true
      },
      "slots.a": [
        "Extreme_Teamwork",
        "Memory_of_a_Friend",
        "Spirit_of_the_Season",
        "A_Passion_for_Produce",
        "A_Small_Courage",
        "Mask_of_Determination_Bow",
        "Testament_of_Eternity"
      ],
      "slots.d": "Gala_Reborn_Jeanne",
      "acl": [
        "`dragon(c3-s-c3-c3-c3-end), aff(flashburn)",
        "`s4",
        "`s3",
        "`s1",
        "`s2, x=5"
      ],
      "coabs": [
        "Blade",
        "Peony",
        "Wand"
      ],
      "share": [
        "Gala_Mym",
        "Ilia"
      ]
    },
    "META": {
      "pref": "PERSONAL",
      "partial": {
        "PERSONAL": "SELF-NIHILISM-ANY",
        "TEAMBUFF": "SELF-NORMAL-ANY"
      }
    }
  }
}