{
  "180": {
    "base": {
      "dps": 56071.253285325045,
      "team": 0.06061464205965501,
      "tdps": null,
      "slots.a": [
        "A_Man_Unchanging",
        "Forest_Bonds",
        "Memory_of_a_Friend",
        "His_Clever_Brother",
        "The_Queen_of_the_Knife"
      ],
      "slots.d": "Gala_Reborn_Zephyr",
      "acl": [
        "`dragon(c3-s-c3-end), s1.check()",
        "`s3, not buff(s3)",
        "`s2, s=1",
        "`s1",
        "`s4"
      ],
      "coabs": [
        "Blade",
        "Dragonyule_Xainfried",
        "Ku_Hai"
      ],
      "share": [
        "Weapon",
        "Xander"
      ]
    },
    "pref": "base",
    "affliction": {
      "dps": 63177.70723802928,
      "team": 0.058667276576899414,
      "tdps": null,
      "slots.a": [
        "A_Man_Unchanging",
        "Forest_Bonds",
        "Memory_of_a_Friend",
        "His_Clever_Brother",
        "The_Queen_of_the_Knife"
      ],
      "slots.d": "Gala_Reborn_Zephyr",
      "acl": [
        "`dragon(c3-s-c3-end), s1.check()",
        "`s3, not buff(s3)",
        "`s2, s=1",
        "`s1",
        "`s4"
      ],
      "coabs": [
        "Blade",
        "Dragonyule_Xainfried",
        "Mona"
      ],
      "share": [
        "Weapon",
        "Pinon"
      ]
    },
    "buffer": {
      "dps": 41111.1607548585,
      "team": 0.0921353839641998,
      "tdps": 474611.0537553539,
      "slots.a": [
        "Dear_Diary",
        "Forest_Bonds",
        "Memory_of_a_Friend",
        "Hastened_Squall",
        "The_Plaguebringer"
      ],
      "slots.d": "Ariel",
      "acl": [
        "`dragon(c3-s-end), s1.check()",
        "`s3, not buff(s3)",
        "`s2, s=1",
        "`s1",
        "`s4"
      ],
      "coabs": [
        "Blade",
        "Dragonyule_Xainfried",
        "Akasha"
      ],
      "share": [
        "Weapon",
        "Curran"
      ]
    },
    "mono_base": {
      "dps": 56071.253285325045,
      "team": 0.06061464205965501,
      "tdps": null,
      "slots.a": [
        "A_Man_Unchanging",
        "Forest_Bonds",
        "Memory_of_a_Friend",
        "His_Clever_Brother",
        "The_Queen_of_the_Knife"
      ],
      "slots.d": "Gala_Reborn_Zephyr",
      "acl": [
        "`dragon(c3-s-c3-end), s1.check()",
        "`s3, not buff(s3)",
        "`s2, s=1",
        "`s1",
        "`s4"
      ],
      "coabs": [
        "Blade",
        "Dragonyule_Xainfried",
        "Ku_Hai"
      ],
      "share": [
        "Weapon",
        "Xander"
      ]
    },
    "mono_buffer": {
      "dps": 41111.1607548585,
      "team": 0.0921353839641998,
      "tdps": 474611.0537553539,
      "slots.a": [
        "Dear_Diary",
        "Forest_Bonds",
        "Memory_of_a_Friend",
        "Hastened_Squall",
        "The_Plaguebringer"
      ],
      "slots.d": "Ariel",
      "acl": [
        "`dragon(c3-s-end), s1.check()",
        "`s3, not buff(s3)",
        "`s2, s=1",
        "`s1",
        "`s4"
      ],
      "coabs": [
        "Blade",
        "Dragonyule_Xainfried",
        "Akasha"
      ],
      "share": [
        "Weapon",
        "Curran"
      ]
    },
    "mono_pref": "mono_base",
    "mono_affliction": {
      "dps": 63177.70723802928,
      "team": 0.058667276576899414,
      "tdps": null,
      "slots.a": [
        "A_Man_Unchanging",
        "Forest_Bonds",
        "Memory_of_a_Friend",
        "His_Clever_Brother",
        "The_Queen_of_the_Knife"
      ],
      "slots.d": "Gala_Reborn_Zephyr",
      "acl": [
        "`dragon(c3-s-c3-end), s1.check()",
        "`s3, not buff(s3)",
        "`s2, s=1",
        "`s1",
        "`s4"
      ],
      "coabs": [
        "Blade",
        "Dragonyule_Xainfried",
        "Mona"
      ],
      "share": [
        "Weapon",
        "Pinon"
      ]
    }
  },
  "60": {
    "affliction": {
      "dps": 56125.15504871628,
      "team": 0.048518716840284554,
      "tdps": null,
      "slots.a": [
        "A_Man_Unchanging",
        "Forest_Bonds",
        "Memory_of_a_Friend",
        "His_Clever_Brother",
        "The_Queen_of_the_Knife"
      ],
      "slots.d": "Midgardsormr_Zero",
      "acl": [
        "`dragon(c3-s-c3-end), s1.check()",
        "`s3, not buff(s3)",
        "`s2, s=1",
        "`s1",
        "`s4"
      ],
      "coabs": [
        "Blade",
        "Dragonyule_Xainfried",
        "Lin_You"
      ],
      "share": [
        "Weapon",
        "Pinon"
      ]
    },
    "pref": "base",
    "mono_affliction": {
      "dps": 56125.15504871628,
      "team": 0.048518716840284554,
      "tdps": null,
      "slots.a": [
        "A_Man_Unchanging",
        "Forest_Bonds",
        "Memory_of_a_Friend",
        "His_Clever_Brother",
        "The_Queen_of_the_Knife"
      ],
      "slots.d": "Midgardsormr_Zero",
      "acl": [
        "`dragon(c3-s-c3-end), s1.check()",
        "`s3, not buff(s3)",
        "`s2, s=1",
        "`s1",
        "`s4"
      ],
      "coabs": [
        "Blade",
        "Dragonyule_Xainfried",
        "Lin_You"
      ],
      "share": [
        "Weapon",
        "Pinon"
      ]
    }
  }
}