{
  "180": {
    "base": {
      "dps": 69218.52443383756,
      "team": 0.11700276464002095,
      "tdps": null,
      "slots.a": [
        "Me_and_My_Bestie",
        "Memory_of_a_Friend",
        "The_Shining_Overlord",
        "His_Clever_Brother",
        "To_the_Extreme"
      ],
      "slots.d": "Gala_Mars",
      "acl": [
        "queue not buff(s3)",
        "`s3;s1;s2;fs,x=2;s4,fsc",
        "end",
        "`dragon,s=2",
        "queue prep and aff(burn)",
        "`s2;s4",
        "end",
        "queue prep and not aff(burn)",
        "`s1;s2;s4",
        "end",
        "`s2, aff(burn)",
        "`s4, cancel",
        "`s1, fsc and not energy()=5",
        "`fs, x=5"
      ],
      "coabs": [
        "Blade",
        "Wand",
        "Joe"
      ],
      "share": [
        "Weapon",
        "Xander"
      ]
    },
    "pref": "base",
    "buffer": {
      "dps": 14877.525780370668,
      "team": 0.8901404904420347,
      "tdps": 70286.31101540971,
      "slots.a": [
        "Honest_Repose",
        "Jewels_of_the_Sun",
        "Warrior_Maiden",
        "From_Whence_He_Comes",
        "Bellathorna"
      ],
      "slots.d": "Horus",
      "acl": [
        "`s2",
        "`s3",
        "`s4, cancel",
        "`fs, x=2"
      ],
      "coabs": [
        "Nobunaga",
        "Gala_Sarisse",
        "Tobias"
      ],
      "share": [
        "Karl",
        "Templar_Hope"
      ]
    },
    "affliction": {
      "dps": 73711.42126835618,
      "team": 0.11108664988155988,
      "tdps": null,
      "slots.a": [
        "Me_and_My_Bestie",
        "Memory_of_a_Friend",
        "The_Shining_Overlord",
        "His_Clever_Brother",
        "To_the_Extreme"
      ],
      "slots.d": "Gala_Mars",
      "acl": [
        "queue not buff(s3)",
        "`s3;s1;s2;fs,x=2;s4,fsc",
        "end",
        "`dragon,s=2",
        "queue prep and aff(burn)",
        "`s2;s4",
        "end",
        "queue prep and not aff(burn)",
        "`s1;s2;s4",
        "end",
        "`s2, aff(burn)",
        "`s4, cancel",
        "`s1, fsc and not energy()=5",
        "`fs, x=3"
      ],
      "coabs": [
        "Blade",
        "Wand",
        "Gala_Sarisse"
      ],
      "share": [
        "Weapon",
        "Xander"
      ]
    }
  },
  "60": {
    "base": {
      "dps": 73814.08647380343,
      "team": 0.08821981767682718,
      "tdps": null,
      "slots.a": [
        "Me_and_My_Bestie",
        "Memory_of_a_Friend",
        "The_Shining_Overlord",
        "His_Clever_Brother",
        "To_the_Extreme"
      ],
      "slots.d": "Gala_Mars",
      "acl": [
        "queue not buff(s3)",
        "`s3;s1;s2;fs,x=2;s4,fsc",
        "end",
        "`dragon,s=2",
        "queue prep and aff(burn)",
        "`s2;s4",
        "end",
        "queue prep and not aff(burn)",
        "`s1;s2;s4",
        "end",
        "`s2, aff(burn)",
        "`s4, cancel",
        "`s1, fsc and not energy()=5",
        "`fs, x=3"
      ],
      "coabs": [
        "Blade",
        "Wand",
        "Joe"
      ],
      "share": [
        "Weapon",
        "Xander"
      ]
    },
    "affliction": {
      "dps": 80088.294583939,
      "team": 0.08816499515333795,
      "tdps": null,
      "slots.a": [
        "Me_and_My_Bestie",
        "Memory_of_a_Friend",
        "The_Shining_Overlord",
        "His_Clever_Brother",
        "To_the_Extreme"
      ],
      "slots.d": "Gala_Mars",
      "acl": [
        "queue not buff(s3)",
        "`s3;s1;s2;fs,x=2;s4,fsc",
        "end",
        "`dragon,s=2",
        "queue prep and aff(burn)",
        "`s2;s4",
        "end",
        "queue prep and not aff(burn)",
        "`s1;s2;s4",
        "end",
        "`s2, aff(burn)",
        "`s4, cancel",
        "`s1, fsc and not energy()=5",
        "`fs, x=3"
      ],
      "coabs": [
        "Blade",
        "Wand",
        "Gala_Sarisse"
      ],
      "share": [
        "Weapon",
        "Xander"
      ]
    },
    "pref": "base",
    "buffer": {
      "dps": 22633.11363516859,
      "team": 0.10989993610817334,
      "tdps": 2360733.083664107,
      "slots.a": [
        "Gentle_Winds",
        "Me_and_My_Bestie",
        "The_Shining_Overlord",
        "From_Whence_He_Comes",
        "Rogues_Banquet"
      ],
      "slots.d": "Gala_Mars",
      "acl": [
        "queue not buff(s3)",
        "`s3;s1;s2;fs,x=2;s4,fsc",
        "end",
        "`dragon,s=2",
        "queue prep and aff(burn)",
        "`s2;s4",
        "end",
        "queue prep and not aff(burn)",
        "`s1;s2;s4",
        "end",
        "`s2, aff(burn)",
        "`s4, cancel",
        "`s1, fsc and not energy()=5",
        "`fs, x=3"
      ],
      "coabs": [
        "Nobunaga",
        "Wand",
        "Halloween_Mym"
      ],
      "share": [
        "Patia",
        "Yue"
      ]
    }
  },
  "120": {
    "base": {
      "dps": 68708.584325771,
      "team": 0.09596154295919379,
      "tdps": null,
      "slots.a": [
        "Me_and_My_Bestie",
        "Memory_of_a_Friend",
        "The_Shining_Overlord",
        "His_Clever_Brother",
        "To_the_Extreme"
      ],
      "slots.d": "Gala_Mars",
      "acl": [
        "queue not buff(s3)",
        "`s3;s1;s2;fs,x=2;s4,fsc",
        "end",
        "`dragon,s=2",
        "queue prep and aff(burn)",
        "`s2;s4",
        "end",
        "queue prep and not aff(burn)",
        "`s1;s2;s4",
        "end",
        "`s2, aff(burn)",
        "`s4, cancel",
        "`s1, fsc and not energy()=5",
        "`fs, x=3"
      ],
      "coabs": [
        "Blade",
        "Wand",
        "Joe"
      ],
      "share": [
        "Weapon",
        "Xander"
      ]
    },
    "pref": "base",
    "buffer": {
      "dps": 57751.37675521783,
      "team": 0.09639728567743089,
      "tdps": 25146048.601530712,
      "slots.a": [
        "Me_and_My_Bestie",
        "Memory_of_a_Friend",
        "The_Shining_Overlord",
        "His_Clever_Brother",
        "To_the_Extreme"
      ],
      "slots.d": "Gala_Mars",
      "acl": [
        "queue not buff(s3)",
        "`s3;s1;s2;fs,x=2;s4,fsc",
        "end",
        "`dragon,s=2",
        "queue prep and aff(burn)",
        "`s2;s4",
        "end",
        "queue prep and not aff(burn)",
        "`s1;s2;s4",
        "end",
        "`s2, aff(burn)",
        "`s4, cancel",
        "`s1, fsc and not energy()=5",
        "`fs, x=3"
      ],
      "coabs": [
        "Blade",
        "Wand",
        "Joe"
      ],
      "share": [
        "Weapon",
        "Zhu_Bajie"
      ]
    },
    "affliction": {
      "dps": 75034.50390017772,
      "team": 0.09648367432637461,
      "tdps": null,
      "slots.a": [
        "Me_and_My_Bestie",
        "Memory_of_a_Friend",
        "The_Shining_Overlord",
        "His_Clever_Brother",
        "To_the_Extreme"
      ],
      "slots.d": "Gala_Mars",
      "acl": [
        "queue not buff(s3)",
        "`s3;s1;s2;fs,x=2;s4,fsc",
        "end",
        "`dragon,s=2",
        "queue prep and aff(burn)",
        "`s2;s4",
        "end",
        "queue prep and not aff(burn)",
        "`s1;s2;s4",
        "end",
        "`s2, aff(burn)",
        "`s4, cancel",
        "`s1, fsc and not energy()=5",
        "`fs, x=3"
      ],
      "coabs": [
        "Blade",
        "Wand",
        "Gala_Sarisse"
      ],
      "share": [
        "Weapon",
        "Xander"
      ]
    }
  }
}