{"180": {"base": {"dps": 72360.50467960139, "team": 0.0, "tdps": null, "output": "-,180,_\n72361,Mikoto,110010_01_r05,flame,blade,4896,Gala Mars,200009_01,Tyrfing,302129_01_60101,Breakfast at Valerio's,400285_02,Moonlight Party,400448_02,Resounding Rendition,400110_02,His Clever Brother,400169_02,To the Extreme!,400095_02,Ezelith,110011_01_r05,Gala Sarisse,100029_02_r05,Halloween Mym,100010_07_r05,Weapon,,Xander,110022_01_r05,always connect hits & hp50 & hp70 & hit15,,frostbite:86.1%,attack:15350,s1:3105,s1_flare:6223,s1_ruin:13312,s4:8992,s4_frostbite:1915,dx:16558,ds:6902\n", "slots.a": ["Breakfast_at_Valerios", "Moonlight_Party", "Resounding_Rendition", "His_Clever_Brother", "To_the_Extreme"], "slots.d": "Gala_Mars", "acl": ["`dragon, s=1", "`s3, not buff(s3)", "`s4", "`s1, cancel", "`s2, x=5"], "coabs": ["Ezelith", "Gala_Sarisse", "Halloween_Mym"], "share": ["Weapon", "Xander"]}, "pref": "base", "burn": {"dps": 85447.54121441732, "team": 0.0, "tdps": null, "output": "-,180,affliction\n85448,Mikoto,110010_01_r05,flame,blade,4896,Gala Mars,200009_01,Tyrfing,302129_01_60101,Breakfast at Valerio's,400285_02,Me and My Bestie!,400435_02,Resounding Rendition,400110_02,His Clever Brother,400169_02,To the Extreme!,400095_02,Ezelith,110011_01_r05,Gala Sarisse,100029_02_r05,Halloween Mym,100010_07_r05,Weapon,,Xander,110022_01_r05,always connect hits & hp50 & hp70 & hit15,,burn:100.0%;frostbite:86.1%,attack:18136,s1:3689,s1_flare:7299,s1_ruin:15701,s4:10663,s4_frostbite:2271,dx:19538,ds:8147\n", "slots.a": ["Breakfast_at_Valerios", "Me_and_My_Bestie", "Resounding_Rendition", "His_Clever_Brother", "To_the_Extreme"], "slots.d": "Gala_Mars", "acl": ["`dragon, s=1", "`s3, not buff(s3)", "`s4", "`s1, cancel", "`s2, x=5"], "coabs": ["Ezelith", "Gala_Sarisse", "Halloween_Mym"], "share": ["Weapon", "Xander"]}}}