{
  "180": {
    "base": {
      "dps": 60098.29515333945,
      "team": 0.0,
      "tdps": null,
      "slots.a": [
        "Dear_Diary",
        "Forest_Bonds",
        "Memory_of_a_Friend",
        "His_Clever_Brother",
        "The_Plaguebringer"
      ],
      "slots.d": "Gala_Cat_Sith",
      "acl": [
        "`s3, not buff(s3) and x=4",
        "`fs, c_fs(enhanced) > 0 and x=4 and s1.check()",
        "`s1, fsc or x=1 or s=4 or not buff(s3)",
        "`s4",
        "`s2"
      ],
      "coabs": [
        "Ieyasu",
        "Wand",
        "Gala_Alex"
      ],
      "share": [
        "Weapon",
        "Karina"
      ]
    },
    "pref": "base",
    "affliction": {
      "dps": 67262.03979195225,
      "team": 0.0,
      "tdps": null,
      "slots.a": [
        "Dear_Diary",
        "Forest_Bonds",
        "Memory_of_a_Friend",
        "His_Clever_Brother",
        "The_Plaguebringer"
      ],
      "slots.d": "Gala_Cat_Sith",
      "acl": [
        "`dragon(c3-s-end)",
        "`s3, not buff(s3) and x=4",
        "`fs, c_fs(enhanced) > 0 and x=4",
        "`s1, fsc or x=1 or s=4 or not buff(s3)",
        "`s4",
        "`s2",
        "`dodge, fsc",
        "`fs, x=4"
      ],
      "coabs": [
        "Ieyasu",
        "Wand",
        "Forte"
      ],
      "share": [
        "Weapon",
        "Pinon"
      ]
    },
    "buffer": {
      "dps": 29315.33150787488,
      "team": 0.12262426290512494,
      "tdps": 251034.8516368373,
      "slots.a": [
        "Dear_Diary",
        "Forest_Bonds",
        "Memory_of_a_Friend",
        "His_Clever_Brother",
        "The_Plaguebringer"
      ],
      "slots.d": "Ramiel",
      "acl": [
        "`s3, not buff(s3) and x=4",
        "`fs, c_fs(enhanced) > 0 and x=4 and s1.check()",
        "`s1, fsc or x=1 or s=4 or not buff(s3)",
        "`s4",
        "`s2"
      ],
      "coabs": [
        "Gala_Alex"
      ],
      "share": [
        "Weapon",
        "Cleo"
      ]
    }
  },
  "120": {
    "base": {
      "dps": 49459.7975060033,
      "team": 0.030955606501665005,
      "tdps": null,
      "slots.a": [
        "Dear_Diary",
        "Forest_Bonds",
        "The_Fires_of_Hate",
        "Seaside_Memory",
        "The_Plaguebringer"
      ],
      "slots.d": "Gala_Cat_Sith",
      "acl": [
        "`dragon(c3-s-end)",
        "`s3, not buff(s3) and x=4",
        "`fs, c_fs(enhanced) > 0 and x=4 and s1.check()",
        "`s1, fsc or x=1 or s=4 or not buff(s3)",
        "`s4",
        "`s2"
      ],
      "coabs": [
        "Wand",
        "Heinwald",
        "Gala_Alex"
      ],
      "share": [
        "Weapon",
        "Summer_Cleo"
      ]
    },
    "affliction": {
      "dps": 68122.73328828868,
      "team": 0.0,
      "tdps": null,
      "slots.a": [
        "Dear_Diary",
        "Forest_Bonds",
        "Memory_of_a_Friend",
        "His_Clever_Brother",
        "The_Plaguebringer"
      ],
      "slots.d": "Gala_Cat_Sith",
      "acl": [
        "`dragon(c3-s-end)",
        "`s3, not buff(s3) and x=4",
        "`fs, c_fs(enhanced) > 0 and x=4",
        "`s1, fsc or x=1 or s=4 or not buff(s3)",
        "`s4",
        "`s2",
        "`dodge, fsc",
        "`fs, x=5"
      ],
      "coabs": [
        "Ieyasu",
        "Wand",
        "Gala_Alex"
      ],
      "share": [
        "Weapon",
        "Karina"
      ]
    },
    "pref": "base"
  },
  "60": {
    "base": {
      "dps": 52111.695390285415,
      "team": 0.0,
      "tdps": -40566.46204854978,
      "slots.a": [
        "Dear_Diary",
        "Forest_Bonds",
        "Memory_of_a_Friend",
        "His_Clever_Brother",
        "The_Plaguebringer"
      ],
      "slots.d": "Gala_Cat_Sith",
      "acl": [
        "`dragon(c3-s-end)",
        "`s3, not buff(s3) and x=4",
        "`fs, c_fs(enhanced) > 0 and x=4 and s1.check()",
        "`s1, fsc or x=1 or s=4 or not buff(s3)",
        "`s4",
        "`s2"
      ],
      "coabs": [
        "Ieyasu",
        "Wand",
        "Gala_Alex"
      ],
      "share": [
        "Weapon",
        "Pinon"
      ]
    },
    "pref": "buffer",
    "buffer": {
      "dps": 54644.61291750709,
      "team": 0.062438709202451245,
      "tdps": -40566.46204854978,
      "slots.a": [
        "Dear_Diary",
        "Forest_Bonds",
        "Memory_of_a_Friend",
        "Snipers_Allure",
        "The_Plaguebringer"
      ],
      "slots.d": "Gala_Cat_Sith",
      "acl": [
        "`dragon(c3-s-end)",
        "`s3, not buff(s3) and x=4",
        "`fs, c_fs(enhanced) > 0 and x=4 and s1.check()",
        "`s1, fsc or x=1 or s=4 or not buff(s3)",
        "`s4",
        "`s2"
      ],
      "coabs": [
        "Ieyasu",
        "Wand",
        "Gala_Alex"
      ],
      "share": [
        "Weapon",
        "Elisanne"
      ]
    },
    "affliction": {
      "dps": 64782.93793413466,
      "team": 0.0,
      "tdps": null,
      "slots.a": [
        "Dear_Diary",
        "Forest_Bonds",
        "Memory_of_a_Friend",
        "His_Clever_Brother",
        "The_Plaguebringer"
      ],
      "slots.d": "Gala_Cat_Sith",
      "acl": [
        "`dragon(c3-s-end)",
        "`s3, not buff(s3) and x=4",
        "`fs, c_fs(enhanced) > 0 and x=4",
        "`s1, fsc or x=1 or s=4 or not buff(s3)",
        "`s4",
        "`s2",
        "`dodge, fsc",
        "`fs, x=5"
      ],
      "coabs": [
        "Ieyasu",
        "Wand",
        "Gala_Alex"
      ],
      "share": [
        "Weapon",
        "Karina"
      ]
    }
  }
}