{
  "180": {
    "base": {
      "dps": 46355.20637053154,
      "team": 0.0,
      "tdps": null,
      "slots.a": [
        "Dear_Diary",
        "Forest_Bonds",
        "Memory_of_a_Friend",
        "His_Clever_Brother",
        "The_Plaguebringer"
      ],
      "slots.d": "Siren",
      "acl": [
        "`dragon, s",
        "`s3, not buff(s3)",
        "`s2, not buff(s2)",
        "`s1",
        "`s4"
      ],
      "coabs": [
        "Blade",
        "Summer_Estelle",
        "Dragonyule_Cleo"
      ],
      "share": [
        "Weapon",
        "Kleimann"
      ]
    },
    "pref": "base",
    "affliction": {
      "dps": 49195.52484779461,
      "team": 0.0,
      "tdps": null,
      "slots.a": [
        "Dear_Diary",
        "Memory_of_a_Friend",
        "The_Lurker_in_the_Woods",
        "Chariot_Drift",
        "His_Clever_Brother"
      ],
      "slots.d": "Nimis",
      "acl": [
        "`dragon, s",
        "`s3, not buff(s3)",
        "if self.unlocked",
        "if x=8 or fsc",
        "`s2",
        "`s4",
        "`s1, energy()=5",
        "end",
        "else",
        "if fsc",
        "`s2",
        "`s4",
        "`s1",
        "`dodge",
        "end",
        "`fs2",
        "end"
      ],
      "coabs": [
        "Blade",
        "Dragonyule_Cleo",
        "Tiki"
      ],
      "share": [
        "Weapon",
        "Yue"
      ]
    },
    "buffer": {
      "dps": 23487.051025063938,
      "team": 0.3067046840407232,
      "tdps": 74560.82849530672,
      "slots.a": [
        "Dear_Diary",
        "Forest_Bonds",
        "Proper_Maintenance",
        "Beach_Battle",
        "His_Clever_Brother"
      ],
      "slots.d": "Gaibhne_and_Creidhne",
      "acl": [
        "`dragon(c3-s-end)",
        "`s3, not buff(s3)",
        "`s4",
        "`s2",
        "`s1"
      ],
      "coabs": [
        "Summer_Estelle",
        "Summer_Celliera",
        "Tobias"
      ],
      "share": [
        "Templar_Hope",
        "Elisanne"
      ]
    }
  },
  "60": {
    "base": {
      "dps": 24900.80358099892,
      "team": 0.0,
      "tdps": null,
      "slots.a": [
        "Forest_Bonds",
        "Memory_of_a_Friend",
        "Moonlight_Party",
        "His_Clever_Brother",
        "The_Queen_of_the_Knife"
      ],
      "slots.d": "Dragonyule_Jeanne",
      "acl": [
        "# `dragon(c3-s-end), s",
        "`s3, not buff(s3)",
        "if self.unlocked",
        "if x=8 or fsc",
        "`s2",
        "`s4",
        "`s1",
        "end",
        "else",
        "if fsc",
        "`s2",
        "`s4",
        "`s1",
        "`dodge",
        "end",
        "`fs2",
        "end"
      ],
      "coabs": [
        "Blade",
        "Dragonyule_Cleo",
        "Tiki"
      ],
      "share": [
        "Weapon",
        "Fjorm"
      ]
    },
    "affliction": {
      "dps": 42345.86774010299,
      "team": 0.0,
      "tdps": null,
      "slots.a": [
        "Dear_Diary",
        "Memory_of_a_Friend",
        "The_Lurker_in_the_Woods",
        "Chariot_Drift",
        "His_Clever_Brother"
      ],
      "slots.d": "Nimis",
      "acl": [
        "`dragon, s",
        "`s3, not buff(s3)",
        "if self.unlocked",
        "if x=8 or fsc",
        "`s2",
        "`s4",
        "`s1, energy()=5",
        "end",
        "else",
        "if fsc",
        "`s2",
        "`s4",
        "`s1",
        "`dodge",
        "end",
        "`fs2",
        "end"
      ],
      "coabs": [
        "Blade",
        "Dragonyule_Cleo",
        "Tiki"
      ],
      "share": [
        "Weapon",
        "Yue"
      ]
    },
    "pref": "base"
  },
  "120": {
    "base": {
      "dps": 39297.23402132306,
      "team": 0.0,
      "tdps": null,
      "slots.a": [
        "Dear_Diary",
        "Memory_of_a_Friend",
        "The_Lurker_in_the_Woods",
        "Chariot_Drift",
        "His_Clever_Brother"
      ],
      "slots.d": "Nimis",
      "acl": [
        "# `dragon(c3-s-end), s",
        "`s3, not buff(s3)",
        "if self.unlocked",
        "if x=8 or fsc",
        "`s2",
        "`s4",
        "`s1",
        "end",
        "else",
        "if fsc",
        "`s2",
        "`s4",
        "`s1",
        "`dodge",
        "end",
        "`fs2",
        "end"
      ],
      "coabs": [
        "Blade",
        "Dragonyule_Cleo",
        "Tiki"
      ],
      "share": [
        "Weapon",
        "Yue"
      ]
    },
    "pref": "base",
    "affliction": {
      "dps": 48669.014089650016,
      "team": 0.0,
      "tdps": null,
      "slots.a": [
        "Dear_Diary",
        "Forest_Bonds",
        "Memory_of_a_Friend",
        "His_Clever_Brother",
        "The_Plaguebringer"
      ],
      "slots.d": "Siren",
      "acl": [
        "`dragon, s",
        "`s3, not buff(s3)",
        "`s2, not buff(s2)",
        "`s1",
        "`s4"
      ],
      "coabs": [
        "Blade",
        "Summer_Estelle",
        "Dragonyule_Cleo"
      ],
      "share": [
        "Weapon",
        "Kleimann"
      ]
    }
  }
}