{"180": {"base": {"dps": 43186.66060856015, "team": 0.0753606523084321, "tdps": null, "output": "-,180,_\n43187,Raemond,110035_01_r03,light,sword,4184,Daikokuten,210110_01,Caladbolg,301141_01_60401,Breakfast at Valerio's,400285_02,Resounding Rendition,400110_02,The Red Impulse,400088_02,A Small Courage,400421_02,Dueling Dancers,400050_02,Lucretia,110305_01_r05,Cleo,100004_01_r04,Peony,110361_01_r05,Weapon,,Kleimann,110051_01_r04,last offense & hit10 & hit15 & hp100,,poison:52.1%;stun:3.6%;team:7.53607%,attack:3342,fs:1578,s1:7745,s2:3749,s3_phase2:2973,s4:3734,s4_poison:736,dx:15840,ds:3486\n", "slots.a": ["Breakfast_at_Valerios", "Resounding_Rendition", "The_Red_Impulse", "A_Small_Courage", "Dueling_Dancers"], "slots.d": "Daikokuten", "acl": ["`dragon", "`s4", "`s1", "`s2, fsc", "`s3, fsc", "`fs, x=2"], "coabs": ["Lucretia", "Cleo", "Peony"], "share": ["Weapon", "Kleimann"]}, "pref": "base", "buffer": {"dps": 35973.678553773476, "team": 0.0756505964561595, "tdps": 24877143.10263708, "output": "-,180,_\n35974,Raemond,110035_01_r03,light,sword,4184,Daikokuten,210110_01,Caladbolg,301141_01_60401,Breakfast at Valerio's,400285_02,Resounding Rendition,400110_02,The Red Impulse,400088_02,A Small Courage,400421_02,Dueling Dancers,400050_02,Lucretia,110305_01_r05,Cleo,100004_01_r04,Peony,110361_01_r05,Weapon,,Kleimann,110051_01_r04,last offense & hit10 & hit15 & hp100,,poison:54.7%;stun:3.5%;team:7.56506%,attack:2951,fs:1698,s1:6824,s2:3425,s3_phase2:2436,s4:3157,s4_poison:679,dx:12095,ds:2705\n", "slots.a": ["Breakfast_at_Valerios", "Resounding_Rendition", "The_Red_Impulse", "A_Small_Courage", "Dueling_Dancers"], "slots.d": "Daikokuten", "acl": ["`dragon", "`s4", "`s1", "`s2, fsc", "`s3, fsc", "`fs, x=2"], "coabs": ["Lucretia", "Cleo", "Peony"], "share": ["Weapon", "Kleimann"]}, "paralysis": {"dps": 46840.17144065255, "team": 0.07485356116364342, "tdps": null, "output": "-,180,affliction\n46840,Raemond,110035_01_r03,light,sword,4184,Daikokuten,210110_01,Caladbolg,301141_01_60401,Breakfast at Valerio's,400285_02,Resounding Rendition,400110_02,Spirit of the Season,400393_02,A Small Courage,400421_02,Dueling Dancers,400050_02,Lucretia,110305_01_r05,Cleo,100004_01_r04,Peony,110361_01_r05,Weapon,,Xander,110022_01_r05,last offense & hit10 & hit15 & hp100,,paralysis:100.0%;frostbite:55.9%;stun:3.6%;team:7.48536%,attack:4110,fs:1997,s1:8357,s2:4077,s3_phase2:3217,s4:3257,s4_frostbite:749,dx:17670,ds:3402\n", "slots.a": ["Breakfast_at_Valerios", "Resounding_Rendition", "Spirit_of_the_Season", "A_Small_Courage", "Dueling_Dancers"], "slots.d": "Daikokuten", "acl": ["`dragon", "`s4", "`s1", "`s2, fsc", "`s3, fsc", "`fs, x=2"], "coabs": ["Lucretia", "Cleo", "Peony"], "share": ["Weapon", "Xander"]}}}