{
  "180": {
    "base": {
      "dps": 49818.54459131927,
      "team": 0.05545602124009982,
      "tdps": null,
      "slots.a": [
        "Forest_Bonds",
        "Me_and_My_Bestie",
        "Memory_of_a_Friend",
        "His_Clever_Brother",
        "To_the_Extreme"
      ],
      "slots.d": "Gala_Mars",
      "acl": [
        "`dragon, s",
        "`s3, not buff(s3)",
        "`s2",
        "`s1, buff(s3)",
        "`s4",
        "`fs, x=5"
      ],
      "coabs": [
        "Blade",
        "Wand",
        "Marth"
      ],
      "share": [
        "Weapon",
        "Pinon"
      ]
    },
    "pref": "base",
    "buffer": {
      "dps": 39199.98260546182,
      "team": 0.05549878646353521,
      "tdps": 248298994.67029426,
      "slots.a": [
        "Forest_Bonds",
        "Memory_of_a_Friend",
        "The_Red_Impulse",
        "A_Small_Courage",
        "Dueling_Dancers"
      ],
      "slots.d": "Gala_Mars",
      "acl": [
        "`dragon, s",
        "`s3, not buff(s3) and fsc",
        "`s2",
        "`s1",
        "`s4",
        "`fs, seq=4"
      ],
      "coabs": [
        "Blade",
        "Wand",
        "Marth"
      ],
      "share": [
        "Weapon",
        "Summer_Patia"
      ]
    },
    "affliction": {
      "dps": 54894.09485679928,
      "team": 0.05545602124009982,
      "tdps": null,
      "slots.a": [
        "Forest_Bonds",
        "Me_and_My_Bestie",
        "Memory_of_a_Friend",
        "His_Clever_Brother",
        "To_the_Extreme"
      ],
      "slots.d": "Gala_Mars",
      "acl": [
        "`dragon, s",
        "`s3, not buff(s3)",
        "`s2",
        "`s1, buff(s3)",
        "`s4",
        "`fs, x=5"
      ],
      "coabs": [
        "Blade",
        "Wand",
        "Marth"
      ],
      "share": [
        "Weapon",
        "Pinon"
      ]
    }
  }
}